[
   {
      "img": "img-1.png",
      "selected": false,
      "brand": "Rolex",
      "description": "Hermes Herbag Zip PM 31 Brides de Gala Toile H Berline Natural Sable Palladium Hardware",
      "currency": "21 400 $",
      "rubles": "1 990 200 ₽"
   },
   {
      "img": "img-1.png",
      "selected": false,
      "brand": "Rolex",
      "description": "Hermes Herbag Zip PM 31 Brides de Gala Toile H Berline Natural Sable Palladium Hardware",
      "currency": "21 400 $",
      "rubles": "1 990 200 ₽"
   },
   {
      "img": "img-1.png",
      "selected": false,
      "brand": "Rolex",
      "description": "Hermes Herbag Zip PM 31 Brides de Gala Toile H Berline Natural Sable Palladium Hardware",
      "currency": "21 400 $",
      "rubles": "1 990 200 ₽"
   },
   {
      "img": "img-1.png",
      "selected": false,
      "brand": "Rolex",
      "description": "Hermes Herbag Zip PM 31 Brides de Gala Toile H Berline Natural Sable Palladium Hardware",
      "currency": "21 400 $",
      "rubles": "1 990 200 ₽"
   },
   {
      "img": "img-1.png",
      "selected": false,
      "brand": "Rolex",
      "description": "Hermes Herbag Zip PM 31 Brides de Gala Toile H Berline Natural Sable Palladium Hardware",
      "currency": "21 400 $",
      "rubles": "1 990 200 ₽"
   },
   {
      "img": "img-1.png",
      "selected": false,
      "brand": "Rolex",
      "description": "Hermes Herbag Zip PM 31 Brides de Gala Toile H Berline Natural Sable Palladium Hardware",
      "currency": "21 400 $",
      "rubles": "1 990 200 ₽"
   },
   {
      "img": "img-1.png",
      "selected": false,
      "brand": "Rolex",
      "description": "Hermes Herbag Zip PM 31 Brides de Gala Toile H Berline Natural Sable Palladium Hardware",
      "currency": "21 400 $",
      "rubles": "1 990 200 ₽"
   },
   {
      "img": "img-1.png",
      "selected": false,
      "brand": "Rolex",
      "description": "Hermes Herbag Zip PM 31 Brides de Gala Toile H Berline Natural Sable Palladium Hardware",
      "currency": "21 400 $",
      "rubles": "1 990 200 ₽"
   },
   {
      "img": "img-1.png",
      "selected": false,
      "brand": "Rolex",
      "description": "Hermes Herbag Zip PM 31 Brides de Gala Toile H Berline Natural Sable Palladium Hardware",
      "currency": "21 400 $",
      "rubles": "1 990 200 ₽"
   }
]